spadepp/__init__.py
spadepp/data_source/__init__.py
spadepp/data_source/base.py
spadepp/detection/__init__.py
spadepp/detection/detector.py
spadepp/detection/signal/__init__.py
spadepp/detection/signal/base.py
spadepp/detection/signal/format.py
spadepp/detection/signal/missing_value.py
spadepp/detection/signal/value.py
spadepp/detection/signalizer.py
spadepp/evaluation/__init__.py
spadepp/evaluation/spader.py
spadepp/labeler/__init__.py
spadepp/labeler/oracle.py
spadepp/main.py
spadepp/models/__init__.py
spadepp/models/fcn.py
spadepp/models/features/__init__.py
spadepp/models/features/base.py
spadepp/models/features/statistics.py
spadepp/models/lr.py
spadepp/models/random_forest.py
spadepp/models/sentence_transformer.py
spadepp/models/transformer.py
spadepp/models/xgboost.py
spadepp/scripts/__init__.py
spadepp/scripts/convert_to_rotom.py
spadepp/semi_supervised/__init__.py
spadepp/semi_supervised/active_learner.py
spadepp/semi_supervised/data_augmentation/__init__.py
spadepp/semi_supervised/data_augmentation/error_generator.py
spadepp/semi_supervised/data_augmentation/label_propagation.py
spadepp/semi_supervised/data_augmentation/transformation_learner.py
spadepp/utils/__init__.py
spadepp/utils/debugger.py
spadepp/utils/helpers.py
spadepp-0.1.5.dist-info/WHEEL
spadepp-0.1.5.dist-info/METADATA
spadepp-0.1.5.dist-info/RECORD
